ariai/__init__.py
ariai/core.py
ariai-0.1.0.dist-info/METADATA
ariai-0.1.0.dist-info/WHEEL
ariai-0.1.0.dist-info/top_level.txt
ariai-0.1.0.dist-info/RECORD
